gamma_scanner/__init__.py
gamma_scanner/cli.py
gamma_scanner/dsl_ast.py
gamma_scanner/dsl_builtins.py
gamma_scanner/dsl_engine.py
gamma_scanner/dsl_interpreter.py
gamma_scanner/dsl_lexer.py
gamma_scanner/dsl_parser.py
gamma_scanner/main.py
gamma_scanner-1.0.6.dist-info/licenses/LICENSE
gamma_scanner-1.0.6.dist-info/METADATA
gamma_scanner-1.0.6.dist-info/WHEEL
gamma_scanner-1.0.6.dist-info/entry_points.txt
gamma_scanner-1.0.6.dist-info/top_level.txt
gamma_scanner-1.0.6.dist-info/RECORD
