Metadata-Version: 2.4
Name: gamma-scanner
Version: 1.0.6
Summary: Advanced string manipulation and pattern matching engine with unique DSL syntax
Home-page: https://github.com/gammascanner/gamma-scanner
Author: Harish Santhanalakshmi Ganesan
Author-email: Harish Santhanalakshmi Ganesan <harishsg99@gmail.com>
Maintainer-email: Harish Santhanalakshmi Ganesan <harishsg99@gmail.com>
License-Expression: MIT
Project-URL: Homepage, https://github.com/gammascanner/gamma-scanner
Project-URL: Bug Reports, https://github.com/gammascanner/gamma-scanner/issues
Project-URL: Source, https://github.com/gammascanner/gamma-scanner
Project-URL: Documentation, https://gamma-scanner.readthedocs.io/
Keywords: security,pattern-matching,dsl,text-analysis,malware-detection
Classifier: Development Status :: 4 - Beta
Classifier: Intended Audience :: Developers
Classifier: Intended Audience :: Information Technology
Classifier: Operating System :: OS Independent
Classifier: Programming Language :: Python :: 3
Classifier: Programming Language :: Python :: 3.8
Classifier: Programming Language :: Python :: 3.9
Classifier: Programming Language :: Python :: 3.10
Classifier: Programming Language :: Python :: 3.11
Classifier: Topic :: Security
Classifier: Topic :: Software Development :: Libraries :: Python Modules
Classifier: Topic :: Text Processing
Classifier: Topic :: Utilities
Requires-Python: >=3.8
License-File: LICENSE
Requires-Dist: build>=1.2.2.post1
Requires-Dist: setuptools>=75.3.2
Requires-Dist: twine>=6.1.0
Provides-Extra: dev
Requires-Dist: pytest>=6.0; extra == "dev"
Requires-Dist: pytest-cov>=2.0; extra == "dev"
Requires-Dist: black>=21.0; extra == "dev"
Requires-Dist: flake8>=3.8; extra == "dev"
Dynamic: author
Dynamic: home-page
Dynamic: license-file
Dynamic: requires-python
